openapi_client/__init__.py
openapi_client/api_client.py
openapi_client/configuration.py
openapi_client/exceptions.py
openapi_client/rest.py
openapi_client/api/__init__.py
openapi_client/api/default_api.py
openapi_client/models/__init__.py
openapi_client/models/message.py
openapi_client/models/messages.py
openapi_client/models/path.py
pyhog-0.0.1.dist-info/METADATA
pyhog-0.0.1.dist-info/WHEEL
pyhog-0.0.1.dist-info/top_level.txt
pyhog-0.0.1.dist-info/RECORD
