Metadata-Version: 2.1
Name: pyhog
Version: 0.0.1
Summary: MailHog API
Home-page: UNKNOWN
Author: OpenAPI Generator community
Author-email: team@openapitools.org
License: UNKNOWN
Keywords: OpenAPI,OpenAPI-Generator,MailHog API
Platform: UNKNOWN
Requires-Dist: urllib3 (>=1.15)
Requires-Dist: six (>=1.10)
Requires-Dist: certifi
Requires-Dist: python-dateutil
